qutorch/__init__.py
qutorch/q_simulator.py
qutorch-0.0.5.dist-info/LICENSE
qutorch-0.0.5.dist-info/METADATA
qutorch-0.0.5.dist-info/WHEEL
qutorch-0.0.5.dist-info/top_level.txt
qutorch-0.0.5.dist-info/RECORD
