Metadata-Version: 2.1
Name: qutorch
Version: 0.0.5
Summary: Quantum circuit simulator based in PyTorch.
Home-page: https://github.com/MarioDuran/qutorch
Author: Mario Duran-Vega, Cuauhtemoc Suarez-Ramirez, Chris Mansell
Author-email: mario.duran.vega@gmail.com
License: UNKNOWN
Platform: UNKNOWN
Classifier: Programming Language :: Python :: 3
Classifier: License :: OSI Approved :: MIT License
Classifier: Operating System :: OS Independent
